terminet/__about__.py
terminet/__init__.py
terminet/entry_points.py
terminet/monitor.py
terminet/network_monitor.py
terminet/network_table.py
terminet/styles.tcss
terminet-0.0.2.dist-info/METADATA
terminet-0.0.2.dist-info/WHEEL
terminet-0.0.2.dist-info/entry_points.txt
terminet-0.0.2.dist-info/licenses/LICENSE.txt
terminet-0.0.2.dist-info/RECORD
